{
  "transferencias": [
    {
      "id": "1",
      "valor": 35,
      "destino": "1212-1",
      "data": "2020-11-04T16:30:10.710Z"
    },
    {
      "id": "2",
      "valor": 40,
      "destino": "1213-1",
      "data": "2020-11-04T21:24:10.710Z"
    },
    {
      "id": "3",
      "valor": 12.5,
      "destino": "1214-1",
      "data": "2020-11-05T21:14:10.710Z"
    },
    {
      "valor": 100,
      "destino": "1234-1",
      "data": "2021-11-03T20:18:16.250Z",
      "id": "NOzTzDD"
    },
    {
      "valor": 255,
      "destino": "123123",
      "data": "2021-11-03T20:20:58.048Z",
      "id": "QIy6YgL"
    },
    {
      "valor": 111,
      "destino": "034345",
      "data": "2021-11-04T02:08:13.454Z",
      "id": "yCTB3bm"
    }
  ]
}